{
  "swagger": "2.0",
  "info": {
    "title": "My API",
    "description": "Description",
    "version": "1.0.0"
  },
  "host": "localhost:5000",
  "basePath": "/",
  "schemes": [
    "http"
  ],
  "securityDefinitions": {
    "bearerAuth": {
      "type": "apiKey",
      "name": "Authorization",
      "scheme": "bearer",
      "in": "header",
      "description": "Enter the token with the `Bearer ` prefix, e.g., \"Bearer YOUR_TOKEN\""
    }
  },
  "paths": {
    "/user/": {
      "post": {
        "description": "",
        "parameters": [
          {
            "name": "authorization",
            "in": "header",
            "type": "string"
          }
        ],
        "responses": {
          "200": {
            "description": "OK"
          }
        }
      }
    },
    "/user/register": {
      "post": {
        "description": "",
        "responses": {
          "default": {
            "description": ""
          }
        }
      }
    },
    "/user/login": {
      "post": {
        "description": "",
        "parameters": [
          {
            "name": "body",
            "in": "body",
            "schema": {
              "type": "object",
              "properties": {
                "password": {
                  "example": "any"
                },
                "email": {
                  "example": "any"
                }
              }
            }
          }
        ],
        "responses": {
          "default": {
            "description": ""
          }
        }
      }
    },
    "/user/logout": {
      "post": {
        "description": "",
        "parameters": [
          {
            "name": "authorization",
            "in": "header",
            "type": "string"
          }
        ],
        "responses": {
          "200": {
            "description": "OK"
          }
        }
      }
    },
    "/admin/admin": {
      "get": {
        "description": "",
        "responses": {
          "200": {
            "description": "OK"
          }
        }
      }
    }
  },
  "security": [
    {
      "bearerAuth": []
    }
  ]
}